torkit/__init__.py
torkit-0.1.0.dev0.dist-info/METADATA
torkit-0.1.0.dev0.dist-info/WHEEL
torkit-0.1.0.dev0.dist-info/top_level.txt
torkit-0.1.0.dev0.dist-info/RECORD
